pdf_stamper/__init__.py
pdf_stamper/cli.py
pdf_stamper/stamper.py
pdf_stamper-0.1.0.dist-info/licenses/LICENSE
pdf_stamper-0.1.0.dist-info/METADATA
pdf_stamper-0.1.0.dist-info/WHEEL
pdf_stamper-0.1.0.dist-info/entry_points.txt
pdf_stamper-0.1.0.dist-info/top_level.txt
pdf_stamper-0.1.0.dist-info/RECORD
