Metadata-Version: 2.4
Name: pdf-stamper
Version: 0.1.0
Summary: A Python library for stamping PDF files with sequential numbers or custom text
Author: Mateus Molina
License-Expression: MIT
Project-URL: Homepage, https://github.com/MateusMolina/pdf-stamper
Project-URL: Repository, https://github.com/MateusMolina/pdf-stamper.git
Project-URL: Issues, https://github.com/MateusMolina/pdf-stamper/issues
Keywords: pdf,stamp,overlay,batch,numbering
Classifier: Development Status :: 4 - Beta
Classifier: Programming Language :: Python :: 3
Classifier: Topic :: Office/Business
Classifier: Topic :: Software Development :: Libraries :: Python Modules
Requires-Python: >=3.8
License-File: LICENSE
Requires-Dist: reportlab>=4.0.0
Requires-Dist: pypdf>=6.0.0
Dynamic: license-file
